MANIFEST.in
README
setup.py
pygenius/__init__.py
pygenius/artists.py
pygenius/pageopen.py
pygenius/pagination.py
pygenius/songs.py
pygenius/wordsearch.py
pygenius.egg-info/PKG-INFO
pygenius.egg-info/SOURCES.txt
pygenius.egg-info/dependency_links.txt
pygenius.egg-info/requires.txt
pygenius.egg-info/top_level.txt