Metadata-Version: 1.0
Name: pygenius
Version: 1.1
Summary: Python module for collecting data from rap songs.
Home-page: UNKNOWN
Author: Roopa Vasudevan
Author-email: roopa.vasudevan@gmail.com
License: UNKNOWN
Platform: UNKNOWN
Classifier: Development Status :: 4 - Beta
Classifier: Intended Audience :: Developers
Classifier: Intended Audience :: Education
Classifier: License :: Freely Distributable
Classifier: Natural Language :: English
